urlive/__init__.py
urlive/__main__.py
urlive/main.py
urlive-0.5.dist-info/METADATA
urlive-0.5.dist-info/WHEEL
urlive-0.5.dist-info/entry_points.txt
urlive-0.5.dist-info/top_level.txt
urlive-0.5.dist-info/RECORD
