Metadata-Version: 2.4
Name: urlive
Version: 0.5
Summary: A URL status checker by GTSivam
Author: Thirumurugan (GTSivam)
Author-email: gtsivam6@gmail.com
Requires-Python: >=3.8, <4.0
Requires-Dist: requests>=2.25.1
Requires-Dist: pandas>=1.3.0
Dynamic: author
Dynamic: author-email
Dynamic: requires-dist
Dynamic: requires-python
Dynamic: summary
